skmultichannel/__init__.py
skmultichannel/channel_scoring.py
skmultichannel/channel_selection.py
skmultichannel/config.py
skmultichannel/cross_validation.py
skmultichannel/ensemble_learning.py
skmultichannel/multichannel_pipeline.py
skmultichannel/parallel.py
skmultichannel/ray_backend.py
skmultichannel/score_selection.py
skmultichannel/single_channel_pipeline.py
skmultichannel/testing_utils.py
skmultichannel/transform_wrappers.py
skmultichannel/utils.py
skmultichannel-0.4a0.dist-info/LICENSE
skmultichannel-0.4a0.dist-info/METADATA
skmultichannel-0.4a0.dist-info/WHEEL
skmultichannel-0.4a0.dist-info/top_level.txt
skmultichannel-0.4a0.dist-info/RECORD
