Metadata-Version: 2.1
Name: skmultichannel
Version: 0.4a0
Summary: multichannel machine learning library with in-pipeline automation
Home-page: https://github.com/ajcallegari/scikit-multichannel
Download-URL: https://github.com/ajcallegari/scikit-multichannel/archive/refs/tags/v0.3-alpha.tar.gz
Author: A. John Callegari Jr.
Author-email: a.john.callegari@gmail.com
License: MIT
Keywords: machine learning,semi-auto-ml,scikit-learn,multichannel pipeline,workflow automation,ensemble learning,machine learning pipeline
License-File: LICENSE
